rust-toolchain.toml
sql_impressao-1.9.0.dist-info/METADATA
sql_impressao-1.9.0.dist-info/WHEEL
sql_impressao-1.9.0.dist-info/licenses/LICENSE
sql_impressao/__init__.py
sql_impressao/sql_impressao.cp311-win_amd64.pyd
sql_impressao-1.9.0.dist-info/RECORD
