Metadata-Version: 2.4
Name: sql-impressao
Version: 1.9.0
Classifier: Development Status :: 5 - Production/Stable
Classifier: Framework :: Django
Classifier: Intended Audience :: Developers
Classifier: Natural Language :: English
Classifier: Operating System :: OS Independent
Classifier: Programming Language :: Python :: 3 :: Only
Classifier: Programming Language :: Python :: 3.9
Classifier: Programming Language :: Python :: 3.10
Classifier: Programming Language :: Python :: 3.11
Classifier: Programming Language :: Python :: 3.12
Classifier: Programming Language :: Python :: 3.13
Classifier: Programming Language :: Python :: 3.14
License-File: LICENSE
Summary: A SQL fingerprinter.
Keywords: SQL
Author-email: Adam Johnson <me@adamj.eu>
License-Expression: MIT
Requires-Python: >=3.9
Project-URL: Changelog, https://github.com/adamchainz/sql-impressao/blob/main/CHANGELOG.rst
Project-URL: Funding, https://adamj.eu/books/
Project-URL: Repository, https://github.com/adamchainz/sql-impressao
